<annotation>
	<folder>motor</folder>
	<filename>60d2f14041e2e9a.jpg</filename>
	<path>/home/oriz_1st/Documents/Project/tensor-research/TensorFlow/image/dataset/motor/60d2f14041e2e9a.jpg</path>
	<source>
		<database>Unknown</database>
	</source>
	<size>
		<width>284</width>
		<height>177</height>
		<depth>3</depth>
	</size>
	<segmented>0</segmented>
	<object>
		<name>motor</name>
		<pose>Unspecified</pose>
		<truncated>0</truncated>
		<difficult>0</difficult>
		<bndbox>
			<xmin>38</xmin>
			<ymin>2</ymin>
			<xmax>246</xmax>
			<ymax>171</ymax>
		</bndbox>
	</object>
</annotation>
