<annotation>
	<folder>motor</folder>
	<filename>833cb2f55d3a856.jpg</filename>
	<path>/home/oriz_1st/Documents/Project/tensor-research/TensorFlow/image/dataset/motor/833cb2f55d3a856.jpg</path>
	<source>
		<database>Unknown</database>
	</source>
	<size>
		<width>259</width>
		<height>194</height>
		<depth>3</depth>
	</size>
	<segmented>0</segmented>
	<object>
		<name>motor</name>
		<pose>Unspecified</pose>
		<truncated>0</truncated>
		<difficult>0</difficult>
		<bndbox>
			<xmin>11</xmin>
			<ymin>17</ymin>
			<xmax>120</xmax>
			<ymax>89</ymax>
		</bndbox>
	</object>
	<object>
		<name>motor</name>
		<pose>Unspecified</pose>
		<truncated>0</truncated>
		<difficult>0</difficult>
		<bndbox>
			<xmin>146</xmin>
			<ymin>15</ymin>
			<xmax>235</xmax>
			<ymax>89</ymax>
		</bndbox>
	</object>
	<object>
		<name>motor</name>
		<pose>Unspecified</pose>
		<truncated>0</truncated>
		<difficult>0</difficult>
		<bndbox>
			<xmin>7</xmin>
			<ymin>112</ymin>
			<xmax>123</xmax>
			<ymax>186</ymax>
		</bndbox>
	</object>
	<object>
		<name>motor</name>
		<pose>Unspecified</pose>
		<truncated>0</truncated>
		<difficult>0</difficult>
		<bndbox>
			<xmin>139</xmin>
			<ymin>112</ymin>
			<xmax>250</xmax>
			<ymax>180</ymax>
		</bndbox>
	</object>
</annotation>
