<annotation>
	<folder>mobil</folder>
	<filename>b1270c7db96e5347.jpg</filename>
	<path>/home/oriz_1st/Documents/Project/tensor-research/TensorFlow/image/dataset/mobil/b1270c7db96e5347.jpg</path>
	<source>
		<database>Unknown</database>
	</source>
	<size>
		<width>1024</width>
		<height>768</height>
		<depth>3</depth>
	</size>
	<segmented>0</segmented>
	<object>
		<name>mobil</name>
		<pose>Unspecified</pose>
		<truncated>0</truncated>
		<difficult>0</difficult>
		<bndbox>
			<xmin>118</xmin>
			<ymin>69</ymin>
			<xmax>958</xmax>
			<ymax>601</ymax>
		</bndbox>
	</object>
</annotation>
