<annotation>
	<folder>mobil_jeep</folder>
	<filename>ba37aea52f83ddb.jpg</filename>
	<path>/home/oriz_1st/Documents/Project/tensor-research/TensorFlow/workspace/scraping_image/images/mobil_jeep/ba37aea52f83ddb.jpg</path>
	<source>
		<database>Unknown</database>
	</source>
	<size>
		<width>299</width>
		<height>168</height>
		<depth>3</depth>
	</size>
	<segmented>0</segmented>
	<object>
		<name>mobil</name>
		<pose>Unspecified</pose>
		<truncated>0</truncated>
		<difficult>0</difficult>
		<bndbox>
			<xmin>27</xmin>
			<ymin>23</ymin>
			<xmax>268</xmax>
			<ymax>166</ymax>
		</bndbox>
	</object>
</annotation>
